scitrera_app_framework/__init__.py
scitrera_app_framework/api/__init__.py
scitrera_app_framework/api/plugins.py
scitrera_app_framework/api/variables.py
scitrera_app_framework/base_plugins/__init__.py
scitrera_app_framework/base_plugins/bg_exec.py
scitrera_app_framework/base_plugins/progress_tracker.py
scitrera_app_framework/core/__init__.py
scitrera_app_framework/core/core.py
scitrera_app_framework/core/plugins.py
scitrera_app_framework/core/util.py
scitrera_app_framework/ext_plugins/__init__.py
scitrera_app_framework/ext_plugins/multi_tenant.py
scitrera_app_framework/ext_plugins/pyroscope_plugin.py
scitrera_app_framework/k8s/__init__.py
scitrera_app_framework/k8s/util.py
scitrera_app_framework/patterns/__init__.py
scitrera_app_framework/patterns/multi_ext.py
scitrera_app_framework/platforms/__init__.py
scitrera_app_framework/platforms/bg_threads.py
scitrera_app_framework/slaunch/__init__.py
scitrera_app_framework/slaunch/constants.py
scitrera_app_framework/slaunch/deploy.py
scitrera_app_framework/slaunch/main.py
scitrera_app_framework/util/__init__.py
scitrera_app_framework/util/async_utils.py
scitrera_app_framework/util/imports.py
scitrera_app_framework/util/misc.py
scitrera_app_framework/util/parsing.py
scitrera_app_framework-0.0.68.dist-info/licenses/LICENSE.txt
scitrera_app_framework-0.0.68.dist-info/METADATA
scitrera_app_framework-0.0.68.dist-info/WHEEL
scitrera_app_framework-0.0.68.dist-info/top_level.txt
scitrera_app_framework-0.0.68.dist-info/RECORD
