Metadata-Version: 2.4
Name: scitrera-app-framework
Version: 0.0.68
Summary: Common Application Framework Code and Utilities
Home-page: https://github.com/scitrera/python-app-framework
Author: Scitrera LLC
Author-email: open-source-team@scitrera.com
Classifier: Development Status :: 4 - Beta
Classifier: Intended Audience :: Developers
Classifier: Programming Language :: Python :: 3
Classifier: License :: OSI Approved :: BSD License
Classifier: Operating System :: OS Independent
Requires-Python: >=3.9
License-File: LICENSE.txt
Requires-Dist: botwinick-utils>=0.0.20
Requires-Dist: vpd
Requires-Dist: python-json-logger>=4.0.0
Dynamic: author
Dynamic: author-email
Dynamic: classifier
Dynamic: description
Dynamic: description-content-type
Dynamic: home-page
Dynamic: license-file
Dynamic: requires-dist
Dynamic: requires-python
Dynamic: summary
